axonbot_slack/__init__.py
axonbot_slack/cli.py
axonbot_slack/main.py
axonbot_slack/version.py
axonbot_slack-1.0.16.dist-info/LICENSE
axonbot_slack-1.0.16.dist-info/METADATA
axonbot_slack-1.0.16.dist-info/WHEEL
axonbot_slack-1.0.16.dist-info/entry_points.txt
axonbot_slack-1.0.16.dist-info/top_level.txt
axonbot_slack-1.0.16.dist-info/RECORD
