Metadata-Version: 2.1
Name: axonbot-slack
Version: 1.0.16
Summary: Axonius Slack Bot
Home-page: https://github.com/Axonius/axonbot_slack
Author: Axonius
Author-email: apiclient@axonius.com
License: MIT
Keywords: axonius,slack,bot
Platform: UNKNOWN
Classifier: Development Status :: 5 - Production/Stable
Classifier: Operating System :: OS Independent
Classifier: Intended Audience :: Developers
Classifier: Natural Language :: English
Classifier: License :: OSI Approved :: MIT License
Classifier: Topic :: Software Development :: Libraries :: Python Modules
Classifier: Programming Language :: Python
Classifier: Programming Language :: Python :: 3
Classifier: Programming Language :: Python :: 3.7
Requires-Python: >=2.7, !=3.0.*, !=3.1.*, !=3.2.*, !=3.3.*
Requires-Dist: axonius-api-client (==1.0.3)
Requires-Dist: slack-machine
Requires-Dist: cachetools
Requires-Dist: python-dotenv
Requires-Dist: click
